psqlpy-0.11.9.dist-info/METADATA
psqlpy-0.11.9.dist-info/WHEEL
psqlpy-0.11.9.dist-info/entry_points.txt
psqlpy-0.11.9.dist-info/licenses/LICENSE
psqlpy.libs/libgcc_s-98a1ef30.so.1
psqlpy/__init__.py
psqlpy/_internal.cpython-310-x86_64-linux-gnu.so
psqlpy/_internal/__init__.pyi
psqlpy/_internal/exceptions.pyi
psqlpy/_internal/extra_types.pyi
psqlpy/_internal/row_factories.pyi
psqlpy/exceptions.py
psqlpy/extra_types.py
psqlpy/py.typed
psqlpy/row_factories.py
psqlpy-0.11.9.dist-info/RECORD
