Metadata-Version: 2.4
Name: psqlpy
Version: 0.11.9
Classifier: Typing :: Typed
Classifier: Topic :: Database
Classifier: Development Status :: 4 - Beta
Classifier: Programming Language :: Rust
Classifier: Programming Language :: Python
Classifier: Operating System :: MacOS
Classifier: Operating System :: Microsoft
Classifier: Operating System :: POSIX :: Linux
Classifier: Intended Audience :: Developers
Classifier: Topic :: Database :: Front-Ends
Classifier: Programming Language :: Python
Classifier: Programming Language :: Python :: 3
Classifier: Programming Language :: Python :: 3 :: Only
Classifier: Programming Language :: Python :: 3.8
Classifier: Programming Language :: Python :: 3.9
Classifier: Programming Language :: Python :: 3.10
Classifier: Programming Language :: Python :: 3.11
Classifier: Programming Language :: Python :: 3.12
Classifier: Programming Language :: Python :: 3.13
Classifier: Programming Language :: Python :: 3.14
License-File: LICENSE
Summary: Async PostgreSQL driver for Python written in Rust
Keywords: postgresql,psql,async-driver,psql-driver,postgresql-driver,python-driver
Author: Kiselev Aleksandr
Author-email: askiselev00@gmail.com
Maintainer-email: Kiselev Aleksandr <askiselev00@gmail.com>
Requires-Python: >=3.8
Project-URL: homepage, https://github.com/psqlpy-python/psqlpy
Project-URL: repository, https://github.com/psqlpy-python/psqlpy
Project-URL: documentation, https://psqlpy-python.github.io/
